CHANGES.txt
LICENSE.txt
MANIFEST.in
README.rst
setup.cfg
setup.py
django_asset_server_url/__init__.py
django_asset_server_url/context_processors.py
django_asset_server_url.egg-info/PKG-INFO
django_asset_server_url.egg-info/SOURCES.txt
django_asset_server_url.egg-info/dependency_links.txt
django_asset_server_url.egg-info/requires.txt
django_asset_server_url.egg-info/top_level.txt