Metadata-Version: 1.0
Name: django-asset-server-url
Version: 0.1
Summary: Provides the URL for an asset server, as a template context variable.
Home-page: https://github.com/ubuntudesign/django-asset-server-url
Author: Robin
Author-email: robin.winslow@canonical.com
License: UNKNOWN
Platform: UNKNOWN
